pymulsim/GIN.py
pymulsim/PyMulSim.py
pymulsim/Utils.py
pymulsim/__init__.py
pymulsim-0.1.1.dist-info/LICENSE
pymulsim-0.1.1.dist-info/METADATA
pymulsim-0.1.1.dist-info/WHEEL
pymulsim-0.1.1.dist-info/top_level.txt
pymulsim-0.1.1.dist-info/RECORD
